coronavirus/__init__.py
coronavirus/apps.py
coronavirus/baker_recipes.py
coronavirus/choices.py
coronavirus/constants.py
coronavirus/settings.py
coronavirus/tests.py
coronavirus/urls.py
coronavirus/wsgi.py
coronavirus/admin/__init__.py
coronavirus/admin/coronavirus_kap_admin.py
coronavirus/admin/modeladmin_mixin.py
coronavirus/forms/__init__.py
coronavirus/forms/coronavirus_kap_form.py
coronavirus/forms/coronavirus_kap_form_validator.py
coronavirus/migrations/0001_initial.py
coronavirus/migrations/__init__.py
coronavirus/model_mixins/__init__.py
coronavirus/model_mixins/coronavirus_kap_model_mixin.py
coronavirus/models/__init__.py
coronavirus/models/coronavirus_kap.py
sarscov2x-1.0.0.dist-info/LICENSE
sarscov2x-1.0.0.dist-info/METADATA
sarscov2x-1.0.0.dist-info/WHEEL
sarscov2x-1.0.0.dist-info/top_level.txt
sarscov2x-1.0.0.dist-info/RECORD
